narnia/__init__.py
narnia/main.py
narnia-0.0.4.dist-info/LICENSE
narnia-0.0.4.dist-info/METADATA
narnia-0.0.4.dist-info/WHEEL
narnia-0.0.4.dist-info/top_level.txt
narnia-0.0.4.dist-info/zip-safe
narnia-0.0.4.dist-info/RECORD
